authl/__init__.py
authl/__version__.py
authl/disposition.py
authl/flask.py
authl/flask_templates/authl.css
authl/flask_templates/login.html
authl/flask_templates/notify.html
authl/flask_templates/post-needed.html
authl/handlers/__init__.py
authl/handlers/email_addr.py
authl/handlers/fediverse.py
authl/handlers/indieauth.py
authl/handlers/test_handler.py
authl/icons/email_addr.svg
authl/icons/indieauth.svg
authl/icons/mastodon.svg
authl/icons/pleroma.svg
authl/tokens.py
authl/utils.py
authl/webfinger.py
authl-0.7.3.dist-info/LICENSE
authl-0.7.3.dist-info/METADATA
authl-0.7.3.dist-info/WHEEL
authl-0.7.3.dist-info/RECORD
