Metadata-Version: 2.1
Name: Authl
Version: 0.7.3
Summary: Framework-agnostic authentication wrapper
Home-page: https://plaidweb.site/
License: MIT
Author: fluffy
Author-email: fluffy@beesbuzz.biz
Requires-Python: >=3.9,<4.0
Classifier: License :: OSI Approved :: MIT License
Classifier: Programming Language :: Python :: 3
Classifier: Programming Language :: Python :: 3.9
Classifier: Programming Language :: Python :: 3.10
Classifier: Programming Language :: Python :: 3.11
Classifier: Programming Language :: Python :: 3.12
Requires-Dist: beautifulsoup4 (>=4.9.1,<5.0.0)
Requires-Dist: expiringdict (>=1.2.1,<2.0.0)
Requires-Dist: itsdangerous (>=1.1.0)
Requires-Dist: mastodon-py (>=1.7.0,<2.0.0)
Requires-Dist: mf2py (>=1.1.2,<2.0.0)
Requires-Dist: requests (>=2.24.0,<3.0.0)
Requires-Dist: requests_oauthlib (>=1.3.0,<2.0.0)
Requires-Dist: validate_email (>=1.3,<2.0)
Project-URL: Documentation, https://authl.readthedocs.io/
Project-URL: Repository, https://github.com/PlaidWeb/Authl
